nutanix_api/__init__.py
nutanix_api/__main__.py
nutanix_api/api_client.py
nutanix_api/base_entity.py
nutanix_api/entity.py
nutanix_api/exceptions.py
nutanix_api/nutanix_cluster.py
nutanix_api/nutanix_image.py
nutanix_api/nutanix_subnet.py
nutanix_api/nutanix_task.py
nutanix_api/nutanix_vm.py
nutanix_api-0.0.20.dist-info/LICENSE
nutanix_api-0.0.20.dist-info/METADATA
nutanix_api-0.0.20.dist-info/WHEEL
nutanix_api-0.0.20.dist-info/top_level.txt
nutanix_api-0.0.20.dist-info/RECORD
