Metadata-Version: 2.1
Name: nutanix-api
Version: 0.0.20
Summary: Library for interact with v3 Nutanix API
Home-page: https://github.com/eliorerz/nutanix_api
Author: Elior Erez
Author-email: elior123@gmail.com
License: MIT
Classifier: Development Status :: 3 - Alpha
Classifier: License :: OSI Approved :: MIT License
Classifier: Operating System :: OS Independent
Classifier: Programming Language :: Python
Classifier: Programming Language :: Python :: 3
Classifier: Programming Language :: Python :: 3.7
Classifier: Programming Language :: Python :: 3.8
Classifier: Programming Language :: Python :: 3.9
Classifier: Topic :: Software Development :: Build Tools
Classifier: Topic :: Software Development :: Testing
Requires-Python: >=3.7.0
License-File: LICENSE
Requires-Dist: requests
Requires-Dist: urllib3
Requires-Dist: waiting
Requires-Dist: python-dateutil
